actions_ips/__init__.py
actions_ips/ips.py
actions_ips-0.3.8.dist-info/LICENSE
actions_ips-0.3.8.dist-info/METADATA
actions_ips-0.3.8.dist-info/WHEEL
actions_ips-0.3.8.dist-info/top_level.txt
actions_ips-0.3.8.dist-info/zip-safe
actions_ips-0.3.8.dist-info/RECORD
