Metadata-Version: 2.1
Name: actions-ips
Version: 0.3.8
Summary: A list of the GitHub Actions IP Addresses
Home-page: https://github.com/andymckay/actions-ips
Author: Andy McKay
Author-email: andymckay@github.com
License: MIT
Platform: UNKNOWN
Classifier: Development Status :: 5 - Production/Stable
Classifier: License :: OSI Approved :: MIT License
Classifier: Operating System :: OS Independent
Classifier: Intended Audience :: Developers
Classifier: Programming Language :: Python :: 3
License-File: LICENSE
Requires-Dist: requests
